usbee/__init__.py
usbee/usbee.cpython-313-x86_64-linux-gnu.so
usbee.libs/libblkid-a9167753.so.1.1.0
usbee.libs/libmount-ec61bd71.so.1.1.0
usbee.libs/libpcre2-8-516f4c9d.so.0.7.1
usbee.libs/libselinux-d0805dcb.so.1
usbee.libs/libudev-9765ffbd.so.1.6.11
usbee.libs/libusb-1-1b307d35.0.so.0.2.0
usbee.libs/libuuid-95b83d40.so.1.3.0
usbee-0.6.1.0.dist-info/METADATA
usbee-0.6.1.0.dist-info/WHEEL
usbee-0.6.1.0.dist-info/top_level.txt
usbee-0.6.1.0.dist-info/RECORD
