Metadata-Version: 2.4
Name: usbee
Version: 0.6.1.0
Summary: SynSense usbee
Author-email: SynSense <carsten.nielsen@synsense.ai>
Requires-Python: >=3.9
